pythai_scb/__init__.py
pythai_scb/config.py
pythai_scb/exceptions.py
pythai_scb/pythai_scb.py
pythai_scb/phantomjs/.DS_Store
pythai_scb/phantomjs/phantomjs_amd64.deb
pythai_scb/phantomjs/phantomjs_linux_32
pythai_scb/phantomjs/phantomjs_linux_64
pythai_scb/phantomjs/phantomjs_mac
pythai_scb/phantomjs/phantomjs_window.exe
pythai_scb-1.0.4.dist-info/LICENSE
pythai_scb-1.0.4.dist-info/METADATA
pythai_scb-1.0.4.dist-info/WHEEL
pythai_scb-1.0.4.dist-info/top_level.txt
pythai_scb-1.0.4.dist-info/RECORD
