Metadata-Version: 2.1
Name: pythai-scb
Version: 1.0.4
Summary: Unofficial SCB Bank Account Balance Check
Home-page: https://github.com/ktantikarun/pythai-scb-unofficial
Author: Krittaboon Tantikarun
Author-email: krittaboon.t@gmail.com
License: MIT License
Project-URL: Bug Reports & Feature Request, https://github.com/ktantikarun/pythai-scb-unofficial/issues
Project-URL: Source, https://github.com/ktantikarun/pythai-scb-unofficial
Keywords: scb,investing-api,accounting-data,financial-data,accountbalance
Platform: UNKNOWN
Classifier: Programming Language :: Python :: 3
Classifier: Programming Language :: Python :: 3.6
Classifier: Programming Language :: Python :: 3.7
Classifier: Programming Language :: Python :: 3.8
Classifier: Programming Language :: Python :: 3.9
Classifier: Programming Language :: Python :: 3.10
Classifier: Programming Language :: Python :: 3.11
Classifier: Programming Language :: Python :: 3.12
Classifier: License :: OSI Approved :: MIT License
Classifier: Intended Audience :: Developers
Classifier: Intended Audience :: Financial and Insurance Industry
Classifier: Intended Audience :: Information Technology
Classifier: Topic :: Office/Business :: Financial
Classifier: Topic :: Office/Business :: Financial :: Accounting
Classifier: Topic :: Scientific/Engineering :: Information Analysis
Classifier: Topic :: Software Development :: Libraries
Requires-Python: >=3.6
License-File: LICENSE
Requires-Dist: beautifulsoup4 (==4.11.1)
Requires-Dist: bs4 (==0.0.1)
Requires-Dist: numpy (==1.23.2)
Requires-Dist: pandas (==1.4.3)
Requires-Dist: python-dateutil (==2.8.2)
Requires-Dist: pytz (==2022.2.1)
Requires-Dist: selenium (==3.7.0)
Requires-Dist: six (==1.16.0)
Requires-Dist: soupsieve (==2.3.2.post1)
